SeleniumCookies/__init__.py
SeleniumCookies/cookie_injector.py
SeleniumCookies/wrapper.py
SeleniumCookies-0.4.dist-info/LICENSE
SeleniumCookies-0.4.dist-info/METADATA
SeleniumCookies-0.4.dist-info/WHEEL
SeleniumCookies-0.4.dist-info/top_level.txt
SeleniumCookies-0.4.dist-info/RECORD
